gptbase/__init__.py
gptbase/base.py
gptbase/chat.py
gptbase/const.py
gptbase-0.3.1.dist-info/METADATA
gptbase-0.3.1.dist-info/WHEEL
gptbase-0.3.1.dist-info/entry_points.txt
gptbase-0.3.1.dist-info/top_level.txt
gptbase-0.3.1.dist-info/RECORD
