Metadata-Version: 2.1
Name: gptbase
Version: 0.3.1
Summary: A package for simplified interaction with OpenAI's GPT-3 and GPT-4 models.
Home-page: https://github.com/callmexss/gptbase
Author: callmexss
Author-email: callmexss@126.com
Classifier: Programming Language :: Python :: 3
Classifier: License :: OSI Approved :: MIT License
Classifier: Operating System :: OS Independent
Requires-Python: >=3.10
Requires-Dist: openai ==1.1.1
Requires-Dist: rich ==13.0.1
Requires-Dist: tiktoken ==0.5.1
Requires-Dist: click ==8.0.3
Requires-Dist: iso-639 ==0.4.5
